{
  "alternatePhrases": [
    "Brun's constant for prime quadruples",
    "Brun's constant for prime quartets"
  ],
  "definition": "[*Brun\u2019s constant for prime quadruplets*]{} is the sum of the\nreciprocals of all prime quadruplets\n$$B_4 = \\sum_{\\substack{p\\\\p + 2 \\text{ is prime}\\\\p + 6 \\text{ is prime}\\\\p + 8 \\text{ is prime}}} \\left(\\frac{1}{p} + \\frac{1}{p + 2} + \\frac{1}{p + 6} + \\frac{1}{p + 8} \\right)\\approx 0.8705883800.$$\n\nViggo Brun proved that the constant exists by using a new sieving\nmethod, which later became known as .",
  "language": "INFORMAL",
  "phrase": "Brun'S Constant For Prime Quadruplets",
  "remarks": "",
  "citations": [
    {
      "textCitation": "https://planetmath.org/BrunsConstantForPrimeQuadruplets"
    }
  ],
  "indexable": true
}